README.md
setup.cfg
setup.py
src/realmz/__init__.py
src/realmz/factory.py
src/realmz/main.py
src/realmz/message.py
src/realmz/operation.py
src/realmz/settings.py
src/realmz/task.py
src/realmz/test_realmz.py
src/realmz.egg-info/PKG-INFO
src/realmz.egg-info/SOURCES.txt
src/realmz.egg-info/dependency_links.txt
src/realmz.egg-info/requires.txt
src/realmz.egg-info/top_level.txt
src/realmz/core/__init__.py
src/realmz/core/employee.py
src/realmz/core/mail.py
src/realmz/core/process.py
src/realmz/db/__init__.py
src/realmz/db/data.py
src/realmz/db/db.py