Metadata-Version: 1.2
Name: realmz
Version: 0.0.17
Summary: To send birthday wishes to employees
Home-page: https://github.com/Billykat7/wishes
Author: Billy Katalayi
Author-email: billysbn7@gmail.com
License: MIT
Project-URL: Bug Tracker, https://github.com/Billykat7/wishes/issues
Keywords: employees birthday,anniversary automated wishes
Platform: UNKNOWN
Classifier: Programming Language :: Python :: 3
Classifier: License :: OSI Approved :: MIT License
Classifier: Operating System :: OS Independent
Requires-Python: >=3.6
